{
    "/js/app.js": "/js/app.js",
    "/css/app.css": "/css/app.css",
    "/js/app.e39046706ae6d72e5cf6.hot-update.js": "/js/app.e39046706ae6d72e5cf6.hot-update.js",
    "/js/app.20e67befa5bcf63763fc.hot-update.js": "/js/app.20e67befa5bcf63763fc.hot-update.js",
    "/js/app.bf743f7ca2a76f84304f.hot-update.js": "/js/app.bf743f7ca2a76f84304f.hot-update.js",
    "/js/app.7d288be157202a4896e0.hot-update.js": "/js/app.7d288be157202a4896e0.hot-update.js",
    "/js/app.3dbd43245f736734e129.hot-update.js": "/js/app.3dbd43245f736734e129.hot-update.js",
    "/js/app.7700bba34dd3bf4415fc.hot-update.js": "/js/app.7700bba34dd3bf4415fc.hot-update.js",
    "/js/app.bb19b4d9e663f8d568fd.hot-update.js": "/js/app.bb19b4d9e663f8d568fd.hot-update.js",
    "/js/app.80db349c823c55d246a8.hot-update.js": "/js/app.80db349c823c55d246a8.hot-update.js",
    "/js/app.228b696858879478c21a.hot-update.js": "/js/app.228b696858879478c21a.hot-update.js",
    "/js/app.0c3f5ff991aaf1db366f.hot-update.js": "/js/app.0c3f5ff991aaf1db366f.hot-update.js",
    "/js/app.dfc04936775dfda765be.hot-update.js": "/js/app.dfc04936775dfda765be.hot-update.js",
    "/js/app.3f9af03a6320dce8f036.hot-update.js": "/js/app.3f9af03a6320dce8f036.hot-update.js",
    "/js/app.6b7b726ea685783a127f.hot-update.js": "/js/app.6b7b726ea685783a127f.hot-update.js",
    "/js/app.ce7bfeb8ec8b7604d7dd.hot-update.js": "/js/app.ce7bfeb8ec8b7604d7dd.hot-update.js",
    "/js/app.27bf54e08664c795749f.hot-update.js": "/js/app.27bf54e08664c795749f.hot-update.js",
    "/js/app.e7014685b0597c1daceb.hot-update.js": "/js/app.e7014685b0597c1daceb.hot-update.js",
    "/js/app.a335084080013f469ed9.hot-update.js": "/js/app.a335084080013f469ed9.hot-update.js",
    "/js/app.6fd434737b8203f42815.hot-update.js": "/js/app.6fd434737b8203f42815.hot-update.js",
    "/js/app.9f5d0998aeb34ac2c68e.hot-update.js": "/js/app.9f5d0998aeb34ac2c68e.hot-update.js",
    "/js/app.1e59e99e47dfaa20a76b.hot-update.js": "/js/app.1e59e99e47dfaa20a76b.hot-update.js",
    "/js/app.7d72226e2c3e57b62f41.hot-update.js": "/js/app.7d72226e2c3e57b62f41.hot-update.js",
    "/js/app.a0ec8c0bbb48347a46c7.hot-update.js": "/js/app.a0ec8c0bbb48347a46c7.hot-update.js",
    "/js/app.1061636e495acb9e870e.hot-update.js": "/js/app.1061636e495acb9e870e.hot-update.js",
    "/js/app.fb37a63695fd9d6ea266.hot-update.js": "/js/app.fb37a63695fd9d6ea266.hot-update.js",
    "/js/app.c8ced64b19a64465b0ed.hot-update.js": "/js/app.c8ced64b19a64465b0ed.hot-update.js",
    "/js/app.acd0714197063bffb043.hot-update.js": "/js/app.acd0714197063bffb043.hot-update.js",
    "/js/app.cf02e58373b2db8203b7.hot-update.js": "/js/app.cf02e58373b2db8203b7.hot-update.js",
    "/js/app.f786f5b6e63db72a6d4d.hot-update.js": "/js/app.f786f5b6e63db72a6d4d.hot-update.js",
    "/js/app.a83dd9699cafaad183dd.hot-update.js": "/js/app.a83dd9699cafaad183dd.hot-update.js",
    "/js/app.e36b8d65bdf090fe4918.hot-update.js": "/js/app.e36b8d65bdf090fe4918.hot-update.js",
    "/js/app.4772db2ff825f49598bd.hot-update.js": "/js/app.4772db2ff825f49598bd.hot-update.js",
    "/js/app.ed45f0057a7eeab0d187.hot-update.js": "/js/app.ed45f0057a7eeab0d187.hot-update.js",
    "/js/app.94d23cf810b48ad2f340.hot-update.js": "/js/app.94d23cf810b48ad2f340.hot-update.js",
    "/js/app.1e855005f33eac457ded.hot-update.js": "/js/app.1e855005f33eac457ded.hot-update.js",
    "/js/app.b9a343a28749f809e98b.hot-update.js": "/js/app.b9a343a28749f809e98b.hot-update.js",
    "/js/app.f91167a5140f2e856450.hot-update.js": "/js/app.f91167a5140f2e856450.hot-update.js",
    "/js/app.4e2811fcfa3831b0a797.hot-update.js": "/js/app.4e2811fcfa3831b0a797.hot-update.js",
    "/js/app.073a64f5ed95c5dc418d.hot-update.js": "/js/app.073a64f5ed95c5dc418d.hot-update.js",
    "/js/app.ebbc6ad44bfb2be3dfa4.hot-update.js": "/js/app.ebbc6ad44bfb2be3dfa4.hot-update.js",
    "/js/app.04306246a3eff8810f33.hot-update.js": "/js/app.04306246a3eff8810f33.hot-update.js",
    "/js/app.a99c348360200a448ef9.hot-update.js": "/js/app.a99c348360200a448ef9.hot-update.js",
    "/js/app.69817eeebdea6b21e777.hot-update.js": "/js/app.69817eeebdea6b21e777.hot-update.js",
    "/js/app.208673f5be6d98ddd202.hot-update.js": "/js/app.208673f5be6d98ddd202.hot-update.js",
    "/js/app.4b96bde41424f3c9d256.hot-update.js": "/js/app.4b96bde41424f3c9d256.hot-update.js",
    "/js/app.addefc75f97ee3d61c2b.hot-update.js": "/js/app.addefc75f97ee3d61c2b.hot-update.js",
    "/js/app.d168bc00ac7b64fccd91.hot-update.js": "/js/app.d168bc00ac7b64fccd91.hot-update.js",
    "/js/app.0fa32d5fb446882e13f3.hot-update.js": "/js/app.0fa32d5fb446882e13f3.hot-update.js",
    "/js/app.f1dcdf111468dc8765cf.hot-update.js": "/js/app.f1dcdf111468dc8765cf.hot-update.js",
    "/js/app.3452b1ad9b495179747c.hot-update.js": "/js/app.3452b1ad9b495179747c.hot-update.js",
    "/js/app.407fb8f7b578ecf8e56f.hot-update.js": "/js/app.407fb8f7b578ecf8e56f.hot-update.js",
    "/js/app.0c9f1e7c6bca0c02d0ce.hot-update.js": "/js/app.0c9f1e7c6bca0c02d0ce.hot-update.js",
    "/js/app.1263f6ba02a3765b8e76.hot-update.js": "/js/app.1263f6ba02a3765b8e76.hot-update.js",
    "/js/app.6fcd3398a40c1cba6d5e.hot-update.js": "/js/app.6fcd3398a40c1cba6d5e.hot-update.js",
    "/js/app.961beed7e9117fa56930.hot-update.js": "/js/app.961beed7e9117fa56930.hot-update.js",
    "/js/app.bc8521b58aff48a5afbf.hot-update.js": "/js/app.bc8521b58aff48a5afbf.hot-update.js",
    "/js/app.3e4c00ac6b0113b3a5cf.hot-update.js": "/js/app.3e4c00ac6b0113b3a5cf.hot-update.js",
    "/js/app.9d05588db80777922114.hot-update.js": "/js/app.9d05588db80777922114.hot-update.js",
    "/js/app.c4b4f8c5530c4a7e24fb.hot-update.js": "/js/app.c4b4f8c5530c4a7e24fb.hot-update.js",
    "/js/app.1a600831603039c0afbb.hot-update.js": "/js/app.1a600831603039c0afbb.hot-update.js",
    "/js/app.77752db168be9e41cd8b.hot-update.js": "/js/app.77752db168be9e41cd8b.hot-update.js",
    "/js/app.8121b98adcad6858e4dd.hot-update.js": "/js/app.8121b98adcad6858e4dd.hot-update.js",
    "/js/app.17808abe2405ed303e42.hot-update.js": "/js/app.17808abe2405ed303e42.hot-update.js",
    "/js/app.f82a0c0344cdfd9f4c16.hot-update.js": "/js/app.f82a0c0344cdfd9f4c16.hot-update.js",
    "/js/app.d5c4f4fd38ba059fae62.hot-update.js": "/js/app.d5c4f4fd38ba059fae62.hot-update.js",
    "/js/app.b68707e03252321960f2.hot-update.js": "/js/app.b68707e03252321960f2.hot-update.js",
    "/js/app.a14b22c50e003cafdd47.hot-update.js": "/js/app.a14b22c50e003cafdd47.hot-update.js",
    "/js/app.29d8182bb4da2399896f.hot-update.js": "/js/app.29d8182bb4da2399896f.hot-update.js",
    "/js/app.f1724a68a8d7ad5b4f67.hot-update.js": "/js/app.f1724a68a8d7ad5b4f67.hot-update.js",
    "/js/app.2bb055f21000dc1683b6.hot-update.js": "/js/app.2bb055f21000dc1683b6.hot-update.js",
    "/js/app.06e6fe92b7641418e926.hot-update.js": "/js/app.06e6fe92b7641418e926.hot-update.js",
    "/js/app.a505696a365057b12d52.hot-update.js": "/js/app.a505696a365057b12d52.hot-update.js",
    "/js/app.a6255fa1abbe08204165.hot-update.js": "/js/app.a6255fa1abbe08204165.hot-update.js",
    "/js/app.2813e2ca22a0a63b868d.hot-update.js": "/js/app.2813e2ca22a0a63b868d.hot-update.js",
    "/js/app.73f7b7ce83141305a650.hot-update.js": "/js/app.73f7b7ce83141305a650.hot-update.js",
    "/js/app.f03adc466edd736ba6b4.hot-update.js": "/js/app.f03adc466edd736ba6b4.hot-update.js",
    "/js/app.1057776da89725da859c.hot-update.js": "/js/app.1057776da89725da859c.hot-update.js",
    "/js/app.c341c650ad3b4c6b7402.hot-update.js": "/js/app.c341c650ad3b4c6b7402.hot-update.js",
    "/js/app.a324d4a603a95e8a8d1e.hot-update.js": "/js/app.a324d4a603a95e8a8d1e.hot-update.js",
    "/js/app.3fd4ff0ba7a19524b0ac.hot-update.js": "/js/app.3fd4ff0ba7a19524b0ac.hot-update.js",
    "/js/app.8588eb246a6db939498c.hot-update.js": "/js/app.8588eb246a6db939498c.hot-update.js",
    "/js/app.5dade92d0b5f5c8d1751.hot-update.js": "/js/app.5dade92d0b5f5c8d1751.hot-update.js",
    "/js/app.e0411cb585305f20f4d1.hot-update.js": "/js/app.e0411cb585305f20f4d1.hot-update.js",
    "/js/app.85dfc6b931aeba3a4482.hot-update.js": "/js/app.85dfc6b931aeba3a4482.hot-update.js",
    "/js/app.96dda47eb0d6ea49c5e7.hot-update.js": "/js/app.96dda47eb0d6ea49c5e7.hot-update.js",
    "/js/app.cd8facd3371a6ddb4dea.hot-update.js": "/js/app.cd8facd3371a6ddb4dea.hot-update.js",
    "/js/app.f9d8a897b54168bbb8ca.hot-update.js": "/js/app.f9d8a897b54168bbb8ca.hot-update.js",
    "/js/app.8ad24f9d70acbc1c3246.hot-update.js": "/js/app.8ad24f9d70acbc1c3246.hot-update.js",
    "/js/app.6cee4156a7f2c4a73bfc.hot-update.js": "/js/app.6cee4156a7f2c4a73bfc.hot-update.js",
    "/js/app.8261269b3966fb1de577.hot-update.js": "/js/app.8261269b3966fb1de577.hot-update.js",
    "/js/app.40627c874178ea147c4b.hot-update.js": "/js/app.40627c874178ea147c4b.hot-update.js",
    "/js/app.637f728620a4c8721026.hot-update.js": "/js/app.637f728620a4c8721026.hot-update.js",
    "/js/app.66b7bfb4ba336a80cd2e.hot-update.js": "/js/app.66b7bfb4ba336a80cd2e.hot-update.js",
    "/js/app.0cb71f26f0a7742d0608.hot-update.js": "/js/app.0cb71f26f0a7742d0608.hot-update.js",
    "/js/app.b0d0f59398f301861133.hot-update.js": "/js/app.b0d0f59398f301861133.hot-update.js",
    "/js/app.dd7bad2a6b17113e1942.hot-update.js": "/js/app.dd7bad2a6b17113e1942.hot-update.js",
    "/js/app.152dd0c89f904cc0f112.hot-update.js": "/js/app.152dd0c89f904cc0f112.hot-update.js",
    "/js/app.e32725e61f7fed8a26c9.hot-update.js": "/js/app.e32725e61f7fed8a26c9.hot-update.js",
    "/js/app.79775757e636b382499a.hot-update.js": "/js/app.79775757e636b382499a.hot-update.js",
    "/js/app.cc6cbf3bf63d77fe55d0.hot-update.js": "/js/app.cc6cbf3bf63d77fe55d0.hot-update.js",
    "/js/app.e7ead0bd961e42784422.hot-update.js": "/js/app.e7ead0bd961e42784422.hot-update.js",
    "/js/app.a2111a1fe8564eb56cbb.hot-update.js": "/js/app.a2111a1fe8564eb56cbb.hot-update.js",
    "/js/app.149c33119acdc6126d97.hot-update.js": "/js/app.149c33119acdc6126d97.hot-update.js",
    "/js/app.9e46b87941546e8a9f7c.hot-update.js": "/js/app.9e46b87941546e8a9f7c.hot-update.js",
    "/js/app.81cc38444ff8ecbdd8af.hot-update.js": "/js/app.81cc38444ff8ecbdd8af.hot-update.js",
    "/js/app.a4a4d6ea81750c636603.hot-update.js": "/js/app.a4a4d6ea81750c636603.hot-update.js",
    "/js/app.dd371e37fcfa62463ed1.hot-update.js": "/js/app.dd371e37fcfa62463ed1.hot-update.js",
    "/js/app.3a10db30e7f9fcc4dfb0.hot-update.js": "/js/app.3a10db30e7f9fcc4dfb0.hot-update.js",
    "/js/app.dec603bd629a6c2e2eb5.hot-update.js": "/js/app.dec603bd629a6c2e2eb5.hot-update.js",
    "/js/app.07deb9c18f6fac33894d.hot-update.js": "/js/app.07deb9c18f6fac33894d.hot-update.js",
    "/js/app.c86fb37c17075e20d29d.hot-update.js": "/js/app.c86fb37c17075e20d29d.hot-update.js",
    "/js/app.70cbaa68ded09ccce27c.hot-update.js": "/js/app.70cbaa68ded09ccce27c.hot-update.js",
    "/js/app.e54c673588579194d13a.hot-update.js": "/js/app.e54c673588579194d13a.hot-update.js",
    "/js/app.66517f820527f382755f.hot-update.js": "/js/app.66517f820527f382755f.hot-update.js",
    "/js/app.f0b21f5e5b7654c387a7.hot-update.js": "/js/app.f0b21f5e5b7654c387a7.hot-update.js"
}
